drogi/__init__.py
drogi/data.py
drogi/destination_chooser.py
drogi/illustrator.py
drogi/main.py
drogi/osm_handler.py
drogi/osmhandler.py
drogi/pathfinder.py
drogi/runtest.py
drogi/trip.py
drogi/waymap.py
drogi/workrun.py
drogi-0.0.15.dist-info/METADATA
drogi-0.0.15.dist-info/RECORD
drogi-0.0.15.dist-info/WHEEL
drogi-0.0.15.dist-info/top_level.txt
