Metadata-Version: 2.1
Name: drogi
Version: 0.0.15
Summary: Tool for analysing urban moveability.
Home-page: https://github.com/mklucz/drogi
Author: Maciej Kluczyński
Author-email: maciej.lukasz.kluczynski@gmail.com
License: UNKNOWN
Platform: UNKNOWN
